{
  "name": "Level 1",
  "background": {
    "image": "background",
    "x": 512,
    "y": 384,
    "alpha": 0.5
  },
  "buildings": [
    {
      "id": "building1",
      "x": 200,
      "y": 500,
      "texture": "building1",
      "scale": 0.5,
      "depth": 100,
      "physics": {
        "bodies": [
          {
            "type": "collision",
            "bodySize": {
              "width": 170,
              "height": 60
            },
            "bodyOffset": {
              "x": 165,
              "y": 225
            }
          },
          {
            "type": "pass-through",
            "bodySize": {
              "width": 200,
              "height": 80
            },
            "bodyOffset": {
              "x": 0,
              "y": -50
            }
          }
        ]
      },
      "door": {
        "enabled": true,
        "openTexture": "building1-door-open",
        "closeDistance": 120,
        "triggerZone": {
          "width": 100,
          "height": 80,
          "offsetX": 50,
          "offsetY": 50
        },
        "interactionZone": {
          "width": 40,
          "height": 20,
          "offsetX": 50,
          "offsetY": 50
        },
        "targetScene": "House1"
      }
    },
    {
      "id": "building2",
      "x": 400,
      "y": 500,
      "texture": "building1",
      "scale": 0.5,
      "depth": 100,
      "physics": {
        "bodies": [
          {
            "type": "collision",
            "bodySize": {
              "width": 170,
              "height": 60
            },
            "bodyOffset": {
              "x": 165,
              "y": 225
            }
          },
          {
            "type": "pass-through",
            "bodySize": {
              "width": 200,
              "height": 80
            },
            "bodyOffset": {
              "x": 0,
              "y": -50
            }
          }
        ]
      },
      "door": {
        "enabled": true,
        "openTexture": "building1-door-open",
        "closeDistance": 120,
        "triggerZone": {
          "width": 100,
          "height": 80,
          "offsetX": 50,
          "offsetY": 50
        },
        "interactionZone": {
          "width": 40,
          "height": 20,
          "offsetX": 50,
          "offsetY": 50
        },
        "targetScene": "House1",
        "targetPosition": {
          "x": 500,
          "y": 100
        }
      }
    },
    {
      "id": "store1",
      "x": 800,
      "y": 190,
      "texture": "store1",
      "scale": 0.7,
      "depth": 100,
      "physics": {
        "bodies": [
          {
            "type": "collision",
            "bodySize": {
              "width": 350,
              "height": 50
            },
            "bodyOffset": {
              "x": 130,
              "y": 185
            }
          },
          {
            "type": "pass-through",
            "bodySize": {
              "width": 370,
              "height": 100
            },
            "bodyOffset": {
              "x": 1,
              "y": -60
            }
          }
        ]
      },
      "door": {
        "enabled": true,
        "openTexture": "store1-door-open",
        "closeDistance": 120,
        "triggerZone": {
          "width": 200,
          "height": 80,
          "offsetX": 50,
          "offsetY": 50
        },
        "interactionZone": {
          "width": 40,
          "height": 20,
          "offsetX": 18,
          "offsetY": 50
        },
        "targetScene": "VincentsStore",
        "targetPosition": {
          "x": 500,
          "y": 100
        }
      }
    }
  ],
  "props": [
    {
      "id": "tree1",
      "x": 200,
      "y": 100,
      "texture": "tree1",
      "depth": 100,
      "physics": {
        "bodies": [
          {
            "type": "collision",
            "bodySize": {
              "width": 70,
              "height": 30
            },
            "bodyOffset": {
              "x": 212,
              "y": 350
            }
          },
          {
            "type": "pass-through",
            "bodySize": {
              "width": 350,
              "height": 210
            },
            "bodyOffset": {
              "x": 0,
              "y": -20
            }
          }
        ]
      }
    }
  ],
  "npcs": [],
  "player": {
    "x": 500,
    "y": 600,
    "depth": 110
  },
  "ui": {
    "text": "",
    "x": 512,
    "y": 84,
    "style": {
      "fontFamily": "Arial Black",
      "fontSize": 24,
      "color": "#ffffff",
      "stroke": "#000000",
      "strokeThickness": 4,
      "align": "right"
    }
  }
}
